odoo/addons/auth_from_http_remote_user_role/README.rst
odoo/addons/auth_from_http_remote_user_role/__init__.py
odoo/addons/auth_from_http_remote_user_role/__manifest__.py
odoo/addons/auth_from_http_remote_user_role/i18n/auth_from_http_remote_user_role.pot
odoo/addons/auth_from_http_remote_user_role/models/__init__.py
odoo/addons/auth_from_http_remote_user_role/models/ir_http.py
odoo/addons/auth_from_http_remote_user_role/models/res_users.py
odoo/addons/auth_from_http_remote_user_role/models/res_users_role.py
odoo/addons/auth_from_http_remote_user_role/static/description/icon.png
odoo/addons/auth_from_http_remote_user_role/tests/__init__.py
odoo/addons/auth_from_http_remote_user_role/tests/tests_user_role_change.py
odoo/addons/auth_from_http_remote_user_role/views/res_users_role.xml
odoo11_addon_auth_from_http_remote_user_role-11.0.1.0.0.99.dev5.dist-info/METADATA
odoo11_addon_auth_from_http_remote_user_role-11.0.1.0.0.99.dev5.dist-info/RECORD
odoo11_addon_auth_from_http_remote_user_role-11.0.1.0.0.99.dev5.dist-info/WHEEL
odoo11_addon_auth_from_http_remote_user_role-11.0.1.0.0.99.dev5.dist-info/top_level.txt
